tykitools/__init__.py
tykitools/main.py
tykitools/scripts/__init__.py
tykitools/scripts/ip_lookup.py
tykitools/scripts/social_media_lookup.py
tykitools-0.2.0.dist-info/licenses/LICENSE
tykitools-0.2.0.dist-info/METADATA
tykitools-0.2.0.dist-info/WHEEL
tykitools-0.2.0.dist-info/top_level.txt
tykitools-0.2.0.dist-info/RECORD
