Metadata-Version: 2.4
Name: tykitools
Version: 0.2.0
Summary: Add your description here
Home-page: https://github.com/tyki6/TykiTools
Author: tyki6
Author-email: matthieubouamama@gmail.com
Requires-Python: >=3.10
License-File: LICENSE
Requires-Dist: click>=8.1.8
Requires-Dist: requests>=2.32.3
Requires-Dist: sherlock-project>=0.15.0
Dynamic: author
Dynamic: author-email
Dynamic: home-page
Dynamic: license-file
Dynamic: requires-python
